xing_tick_crawler/__init__.py
xing_tick_crawler/api.py
xing_tick_crawler/constant.py
xing_tick_crawler/crawler.py
xing_tick_crawler/event_handler.py
xing_tick_crawler/real_time.py
xing_tick_crawler/tick_writer.py
xing_tick_crawler/utils.py
xing_tick_crawler-0.0.7.dist-info/METADATA
xing_tick_crawler-0.0.7.dist-info/WHEEL
xing_tick_crawler-0.0.7.dist-info/top_level.txt
xing_tick_crawler-0.0.7.dist-info/RECORD
