Metadata-Version: 2.1
Name: xing-tick-crawler
Version: 0.0.7
Summary: ebest xing api wrapper
Home-page: https://github.com/quantrading/xing-tick-crawler
Author: Jang Woo Jae
Author-email: woojae.jang26@gmail.com
License: MIT
Platform: UNKNOWN
Requires-Python: >=3
Requires-Dist: pandas
Requires-Dist: pywin32
